mcPAModelpy/CatalyticEvent.py
mcPAModelpy/Constraints.py
mcPAModelpy/Enzyme.py
mcPAModelpy/EnzymeSectors.py
mcPAModelpy/MembraneSector.py
mcPAModelpy/PAMValidator.py
mcPAModelpy/__init__.py
mcPAModelpy/configuration.py
mcPAModelpy/mcPAModel.py
mcPAModelpy/test.py
mcPAMpy-0.0.1.dist-info/LICENSE
mcPAMpy-0.0.1.dist-info/METADATA
mcPAMpy-0.0.1.dist-info/WHEEL
mcPAMpy-0.0.1.dist-info/top_level.txt
mcPAMpy-0.0.1.dist-info/RECORD
