Metadata-Version: 2.1
Name: mcPAMpy
Version: 0.0.1
Summary: membrane-constrained PAModelpy - PAModelpy with additional cell membrane limitation
Author-email: Titania Sugiarto <titania.sugiarto@rwth-aachen.de>
Project-URL: Homepage, https://github.com/titaniasugiarto?tab=projects
Project-URL: Issues, https://github.com/pypa/sampleproject/issues
Classifier: Programming Language :: Python :: 3
Classifier: License :: OSI Approved :: MIT License
Classifier: Operating System :: OS Independent
Requires-Python: >=3.8
License-File: LICENSE
